src/__init__.py
src/server.py
src/splunk_client.py
src/cli/build_and_run.py
src/cli/test_mcp_server.py
src/client/__init__.py
src/client/splunk_client.py
src/core/__init__.py
src/core/base.py
src/core/client_identity.py
src/core/context.py
src/core/discovery.py
src/core/enhanced_config_extractor.py
src/core/loader.py
src/core/registry.py
src/core/security.py
src/core/security_monitoring.py
src/core/shared_context.py
src/core/utils.py
src/core/sentry/__init__.py
src/core/sentry/config.py
src/core/sentry/context.py
src/core/sentry/decorators.py
src/core/sentry/http_middleware.py
src/core/sentry/mcp_middleware.py
src/prompts/__init__.py
src/prompts/dashboard_studio_builder.md
src/prompts/mcp_usage.py
src/resources/__init__.py
src/resources/base.py
src/resources/dashboard_studio_docs.py
src/resources/embedded.py
src/resources/embedded_splunk_docs.py
src/resources/splunk_cim.py
src/resources/splunk_config.py
src/resources/splunk_docs.py
src/resources/processors/__init__.py
src/resources/processors/html_processor.py
src/routes/__init__.py
src/routes/health.py
src/routes/templates.py
src/routes/static/health.css
src/routes/templates/health.html
src/tools/__init__.py
src/tools/admin/__init__.py
src/tools/admin/app_management.py
src/tools/admin/apps.py
src/tools/admin/config.py
src/tools/admin/me.py
src/tools/admin/tool_enhancer.py
src/tools/admin/users.py
src/tools/alerts/__init__.py
src/tools/alerts/alerts.py
src/tools/dashboards/__init__.py
src/tools/dashboards/create_dashboard.py
src/tools/dashboards/get_dashboard_definition.py
src/tools/dashboards/list_dashboards.py
src/tools/docs/__init__.py
src/tools/docs/splunk_docs_tools.py
src/tools/health/__init__.py
src/tools/health/status.py
src/tools/kvstore/__init__.py
src/tools/kvstore/collections.py
src/tools/kvstore/data.py
src/tools/lookups/__init__.py
src/tools/lookups/list_lookup_definitions.py
src/tools/lookups/list_lookup_files.py
src/tools/metadata/__init__.py
src/tools/metadata/get_metadata.py
mcp_server_for_splunk-0.5.0.dist-info/METADATA
mcp_server_for_splunk-0.5.0.dist-info/WHEEL
mcp_server_for_splunk-0.5.0.dist-info/entry_points.txt
mcp_server_for_splunk-0.5.0.dist-info/licenses/LICENSE
mcp_server_for_splunk-0.5.0.dist-info/licenses/NOTICE
mcp_server_for_splunk-0.5.0.dist-info/RECORD
