Metadata-Version: 2.4
Name: mcp-server-for-splunk
Version: 0.5.0
Summary: MCP server for Splunk
Project-URL: Homepage, https://github.com/deslicer/mcp-server-for-splunk
Author-email: MCP for Splunk <developer@example.com>
License: Apache License
License-File: LICENSE
License-File: NOTICE
Keywords: mcp,model-context-protocol,splunk
Classifier: Development Status :: 3 - Alpha
Classifier: Intended Audience :: Developers
Classifier: Programming Language :: Python :: 3
Classifier: Programming Language :: Python :: 3.10
Classifier: Programming Language :: Python :: 3.11
Classifier: Programming Language :: Python :: 3.12
Requires-Python: >=3.10
Requires-Dist: arize-phoenix>=5.0.0
Requires-Dist: beautifulsoup4>=4.12.0
Requires-Dist: fastmcp>=2.13.0.2
Requires-Dist: httpx>=0.27.0
Requires-Dist: mcp[cli]>=1.8.1
Requires-Dist: openai-agents>=0.1.0
Requires-Dist: openai>=1.0.0
Requires-Dist: openinference-instrumentation-mcp>=0.1.0
Requires-Dist: opentelemetry-exporter-otlp-proto-http>=1.27.0
Requires-Dist: python-dotenv>=1.0.0
Requires-Dist: splunk-sdk>=2.1.0
Requires-Dist: uvicorn>=0.32.0
Requires-Dist: wsproto>=1.2.0
Provides-Extra: dev
Requires-Dist: black>=23.0.0; extra == 'dev'
Requires-Dist: mypy>=1.0.0; extra == 'dev'
Requires-Dist: pre-commit>=3.7.0; extra == 'dev'
Requires-Dist: pytest-asyncio>=0.21.0; extra == 'dev'
Requires-Dist: pytest>=7.0.0; extra == 'dev'
Requires-Dist: ruff>=0.1.0; extra == 'dev'
Provides-Extra: docs
Provides-Extra: security
Requires-Dist: bandit>=1.7.0; extra == 'security'
Requires-Dist: safety>=2.3.0; extra == 'security'
Requires-Dist: semgrep>=1.0.0; extra == 'security'
Provides-Extra: sentry
Requires-Dist: sentry-sdk[asyncio,httpx,mcp,starlette]>=2.0.0; extra == 'sentry'
Provides-Extra: test
Requires-Dist: asgi-lifespan>=2.1.0; extra == 'test'
Requires-Dist: pytest-asyncio>=0.21.0; extra == 'test'
Requires-Dist: pytest-cov>=4.0.0; extra == 'test'
Requires-Dist: pytest>=7.0.0; extra == 'test'
